MeTEA/__init__.py
MeTEA/comparator.py
MeTEA/confusion_matrix.py
MeTEA/precall.py
MeTEA/profile_parser.py
MeTEA-0.0.4.dist-info/LICENSE
MeTEA-0.0.4.dist-info/METADATA
MeTEA-0.0.4.dist-info/WHEEL
MeTEA-0.0.4.dist-info/top_level.txt
MeTEA-0.0.4.dist-info/RECORD
