Metadata-Version: 2.1
Name: MeTEA
Version: 0.0.4
Summary: A package to parse, organize, calculate, and save data from metagenomic profile files
Home-page: https://github.com/mag535/MeTEA/
Author: Melissa Gray
Author-email: mag535@drexel.edu
License: UNKNOWN
Platform: UNKNOWN
Classifier: Operating System :: OS Independent
Classifier: Intended Audience :: Science/Research
Classifier: Programming Language :: Python :: 3
Classifier: Programming Language :: Python :: 3.7
Classifier: License :: OSI Approved :: GNU General Public License v3 (GPLv3)
Requires-Python: >=3.7
License-File: LICENSE
